pageforge/__init__.py
pageforge/api.py
pageforge/cli.py
pageforge/py.typed
pageforge/core/__init__.py
pageforge/core/builder.py
pageforge/core/exceptions.py
pageforge/core/models.py
pageforge/engines/DejaVuSans.ttf
pageforge/engines/__init__.py
pageforge/engines/dejavu.zip
pageforge/engines/engine_base.py
pageforge/engines/reportlab_engine.py
pageforge/engines/weasyprint_engine.py
pageforge/rendering/__init__.py
pageforge/rendering/fonts.py
pageforge/rendering/styles.py
pageforge/templating/__init__.py
pageforge/templating/fragments.py
pageforge/templating/template.py
pageforge/templating/templates.py
pageforge/utils/__init__.py
pageforge/utils/config.py
pageforge/utils/logging_config.py
pageforge/utils/storage.py
pageforge-0.1.0.dist-info/licenses/LICENSE
pageforge-0.1.0.dist-info/METADATA
pageforge-0.1.0.dist-info/WHEEL
pageforge-0.1.0.dist-info/entry_points.txt
pageforge-0.1.0.dist-info/top_level.txt
pageforge-0.1.0.dist-info/RECORD
