Metadata-Version: 2.4
Name: pageforge
Version: 0.1.0
Summary: Flexible, extensible PDF/document generation library for LLM & programmatic pipelines.
Author-email: PageForge Team <mxolisi1025@gmail.com>
License: MIT License
Project-URL: Homepage, https://github.com/iCreature/pageforge
Project-URL: Issues, https://github.com/iCreature/pageforge/issues
Project-URL: Changelog, https://github.com/iCreature/pageforge/blob/main/CHANGELOG.md
Project-URL: Documentation, https://pageforge.readthedocs.io/
Keywords: pdf,document,generation,reportlab,pypdf,llm,automation
Classifier: Development Status :: 3 - Alpha
Classifier: Intended Audience :: Developers
Classifier: License :: OSI Approved :: MIT License
Classifier: Programming Language :: Python :: 3
Classifier: Programming Language :: Python :: 3.10
Classifier: Programming Language :: Python :: 3.11
Classifier: Programming Language :: Python :: 3.12
Classifier: Topic :: Software Development :: Libraries :: Python Modules
Classifier: Topic :: Text Processing :: General
Requires-Python: >=3.9
License-File: LICENSE
Requires-Dist: reportlab<5,>=4.0.9
Requires-Dist: pypdf<5,>=4.0
Requires-Dist: pillow>=9.0.0
Provides-Extra: weasy
Requires-Dist: weasyprint<62,>=61; extra == "weasy"
Provides-Extra: dev
Requires-Dist: pytest; extra == "dev"
Requires-Dist: pytest-cov; extra == "dev"
Requires-Dist: ruff; extra == "dev"
Requires-Dist: mypy; extra == "dev"
Requires-Dist: build; extra == "dev"
Requires-Dist: twine; extra == "dev"
Requires-Dist: pytest-benchmark>=4.0.0; extra == "dev"
Requires-Dist: pytest-lazy-fixture>=0.6.0; extra == "dev"
Requires-Dist: hypothesis>=6.0.0; extra == "dev"
Requires-Dist: pdf2image>=1.16.0; extra == "dev"
Requires-Dist: imagehash>=4.3.0; extra == "dev"
Provides-Extra: docs
Requires-Dist: sphinx; extra == "docs"
Requires-Dist: furo; extra == "docs"
Requires-Dist: sphinx-rtd-theme>=1.2.0; extra == "docs"
Requires-Dist: sphinx-autodoc-typehints>=1.23.0; extra == "docs"
Requires-Dist: myst-parser>=2.0.0; extra == "docs"
Dynamic: license-file
